shape_calculator_top/__init__.py
shape_calculator_top/calculator.py
shape_calculator_top-0.1.dist-info/METADATA
shape_calculator_top-0.1.dist-info/WHEEL
shape_calculator_top-0.1.dist-info/top_level.txt
shape_calculator_top-0.1.dist-info/RECORD
